dp_json_util/__init__.py
dp_json_util/retriever.py
dp_json_util-2.0.0.dist-info/LICENSE
dp_json_util-2.0.0.dist-info/METADATA
dp_json_util-2.0.0.dist-info/WHEEL
dp_json_util-2.0.0.dist-info/top_level.txt
dp_json_util-2.0.0.dist-info/RECORD
